{
  "LastUpdated": "2021-08-08T01:24:26+00:00",
  "UserGifts": {
    "118901840": [
      {
        "Id": 7009,
        "AvatarItemDesc": "d0a9262f-5504-46a7-bb10-7507503db58e,14afd295-bcd0-4595-80dc-d477618b9ab9,2ee3944d-e9fb-4959-973e-570a7fc6cc57,a74e6c0d-1300-4928-9141-977a711b71c4",
        "ConsumableItemDesc": "",
        "EquipmentPrefabName": "",
        "EquipmentModificationGuid": "",
        "CurrencyType": 0,
        "Currency": 0,
        "Xp": 0,
        "Level": 0,
        "GiftRarity": 50,
        "Message": "lol",
        "Context": 2
      },
      {
        "UserGifts":69420,
        "Id": 7009,
        "AvatarItemDesc": "e15b13a7-9e9a-4b32-ba2c-0cb31ed55a8c,,,",
        "ConsumableItemDesc": "",
        "EquipmentPrefabName": "",
        "EquipmentModificationGuid": "",
        "CurrencyType": 0,
        "Currency": 0,
        "Xp": 0,
        "Level": 0,
        "GiftRarity": 50,
        "Message": "lol",
        "Context": 2
      },
    ]
  }
}

